dynamicads/__init__.py
dynamicads/client.py
dynamicads/exceptions.py
dynamicads/models.py
dynamicads-2.0.1.dist-info/METADATA
dynamicads-2.0.1.dist-info/WHEEL
dynamicads-2.0.1.dist-info/top_level.txt
dynamicads-2.0.1.dist-info/RECORD
