Metadata-Version: 2.1
Name: dynamicads
Version: 2.0.1
Summary: Official Python SDK for DynamicAds API
Home-page: https://github.com/dynamicads/python-sdk
Author: DynamicAds
Author-email: support@dynamicads.dev
Classifier: Development Status :: 5 - Production/Stable
Classifier: Intended Audience :: Developers
Classifier: License :: OSI Approved :: MIT License
Classifier: Operating System :: OS Independent
Classifier: Programming Language :: Python :: 3
Classifier: Programming Language :: Python :: 3.7
Classifier: Programming Language :: Python :: 3.8
Classifier: Programming Language :: Python :: 3.9
Classifier: Programming Language :: Python :: 3.10
Classifier: Topic :: Software Development :: Libraries :: Python Modules
Requires-Python: >=3.7
Requires-Dist: requests >=2.25.0
Requires-Dist: dataclasses >=0.6 ; python_version < "3.7"
